pytorch_concepts-0.0.12.dist-info/licenses/LICENSE
torch_concepts/__init__.py
torch_concepts/_version.py
torch_concepts/base.py
torch_concepts/metrics.py
torch_concepts/semantic.py
torch_concepts/utils.py
torch_concepts/assets/__init__.py
torch_concepts/assets/ambulance.png
torch_concepts/assets/lights.png
torch_concepts/assets/single_lane_road_intersection.png
torch_concepts/assets/white_black_car.png
torch_concepts/assets/white_car.png
torch_concepts/data/__init__.py
torch_concepts/data/awa2.py
torch_concepts/data/cebab.py
torch_concepts/data/celeba.py
torch_concepts/data/cub.py
torch_concepts/data/mnist.py
torch_concepts/data/toy.py
torch_concepts/data/traffic.py
torch_concepts/data/utils.py
torch_concepts/data/traffic_construction/README.md
torch_concepts/data/traffic_construction/__init__.py
torch_concepts/data/traffic_construction/cars.py
torch_concepts/data/traffic_construction/generate_data.py
torch_concepts/data/traffic_construction/intersection.py
torch_concepts/data/traffic_construction/lights.py
torch_concepts/data/traffic_construction/shared.py
torch_concepts/data/traffic_construction/utils.py
torch_concepts/nn/__init__.py
torch_concepts/nn/base.py
torch_concepts/nn/bottleneck.py
torch_concepts/nn/functional.py
torch_concepts/nn/minimize_constraint.py
torch_concepts/nn/models.py
pytorch_concepts-0.0.12.dist-info/METADATA
pytorch_concepts-0.0.12.dist-info/WHEEL
pytorch_concepts-0.0.12.dist-info/top_level.txt
pytorch_concepts-0.0.12.dist-info/RECORD
